abckeys/__init__.py
abckeys/schemas.py
abckeys-0.1.0.dist-info/METADATA
abckeys-0.1.0.dist-info/WHEEL
abckeys-0.1.0.dist-info/RECORD
